axyutils/__init__.py
axyutils/file_io.py
axyutils/to_string.py
axyutils-0.0.4.dist-info/LICENSE
axyutils-0.0.4.dist-info/METADATA
axyutils-0.0.4.dist-info/WHEEL
axyutils-0.0.4.dist-info/top_level.txt
axyutils-0.0.4.dist-info/RECORD
