Metadata-Version: 2.1
Name: axyutils
Version: 0.0.4
Summary: Declassed utilities
Home-page: https://declassed.art/repository/axyutils
Author: AXY
Author-email: axy@declassed.art
License: UNKNOWN
Platform: UNKNOWN
Classifier: Programming Language :: Python :: 3
Classifier: License :: OSI Approved :: BSD License
Classifier: Operating System :: OS Independent
Classifier: Intended Audience :: Developers
Classifier: Development Status :: 3 - Alpha
Requires-Python: >=3.6
